shield_data/__init__.py
shield_data/_version.py
shield_data/build_catalogue.py
shield_data/core.py
shield_data/data_upload_handler.py
shield_data/pr_template.md
shield_data-0.1.dist-info/licenses/LICENSE
shield_data-0.1.dist-info/METADATA
shield_data-0.1.dist-info/WHEEL
shield_data-0.1.dist-info/top_level.txt
shield_data-0.1.dist-info/RECORD
