Metadata-Version: 2.4
Name: SHIELD_DATA
Version: 0.1
Summary: A database for results collected from the SHIELD permeation rig
Author: James Dark
Author-email: darkj385@mit.edu
License: MIT License
Project-URL: Homepage, https://github.com/PTTEPxMIT/SHIELD-DATA
Project-URL: Issues, https://github.com/PTTEPxMIT/SHIELD-DATA/issues
Classifier: Natural Language :: English
Classifier: Topic :: Scientific/Engineering
Classifier: Programming Language :: Python :: 3.9
Classifier: Programming Language :: Python :: 3.10
Classifier: Programming Language :: Python :: 3.11
Classifier: Programming Language :: Python :: 3.12
Classifier: Programming Language :: Python :: 3.13
Classifier: License :: OSI Approved :: Apache Software License
Classifier: Operating System :: OS Independent
Requires-Python: >=3.9
License-File: LICENSE
Requires-Dist: watchdog
Requires-Dist: jinja2
Requires-Dist: pandas
Provides-Extra: test
Requires-Dist: pytest; extra == "test"
Requires-Dist: pytest-cov; extra == "test"
Provides-Extra: lint
Requires-Dist: ruff; extra == "lint"
Requires-Dist: mypy; extra == "lint"
Dynamic: license-file
